rq_dashboard_fast/__init__.py
rq_dashboard_fast/rq_dashboard_fast.py
rq_dashboard_fast/static/css/main.css
rq_dashboard_fast/templates/base.html
rq_dashboard_fast/templates/export.html
rq_dashboard_fast/templates/footer.html
rq_dashboard_fast/templates/header.html
rq_dashboard_fast/templates/job.html
rq_dashboard_fast/templates/jobs.html
rq_dashboard_fast/templates/queues.html
rq_dashboard_fast/templates/workers.html
rq_dashboard_fast/utils/__init__.py
rq_dashboard_fast/utils/jobs.py
rq_dashboard_fast/utils/queues.py
rq_dashboard_fast/utils/workers.py
rq_dashboard_fast-0.5.12.dist-info/LICENSE.md
rq_dashboard_fast-0.5.12.dist-info/METADATA
rq_dashboard_fast-0.5.12.dist-info/WHEEL
rq_dashboard_fast-0.5.12.dist-info/RECORD
