Metadata-Version: 2.3
Name: rq-dashboard-fast
Version: 0.5.12
Summary: rq-dashboard-fast is a FastAPI-based dashboard to monitor your Redis-Queue (RQ) Jobs, Queues, and Workers
Author: Hannes221
Author-email: hannespfau@gmail.com
Requires-Python: >=3.10,<4.0
Classifier: Programming Language :: Python :: 3
Classifier: Programming Language :: Python :: 3.10
Classifier: Programming Language :: Python :: 3.11
Classifier: Programming Language :: Python :: 3.12
Classifier: Programming Language :: Python :: 3.13
Requires-Dist: fastapi (>=0.109)
Requires-Dist: jinja2 (>=3.1.3)
Requires-Dist: pygments (>=2.18.0,<3.0.0)
Requires-Dist: redis (>=5.0.1)
Requires-Dist: rq (>=1.15.1)
Requires-Dist: rq-scheduler (>=0.13.1)
Requires-Dist: uvicorn (>=0.30)
